altinn/__init__.py
altinn/__main__.py
altinn/file.py
altinn/flatten.py
altinn/parser.py
altinn/py.typed
altinn/utils.py
ssb_altinn_python-0.4.18.dist-info/METADATA
ssb_altinn_python-0.4.18.dist-info/WHEEL
ssb_altinn_python-0.4.18.dist-info/entry_points.txt
ssb_altinn_python-0.4.18.dist-info/licenses/LICENSE
ssb_altinn_python-0.4.18.dist-info/RECORD
