Metadata-Version: 2.4
Name: ssb-altinn-python
Version: 0.4.18
Summary: SSB Altinn Python
License-Expression: MIT
License-File: LICENSE
Author: Vidar Strandseter
Author-email: vidar.strandseter@ssb.no
Maintainer: Statistics Norway, Data enablement Department (724)
Requires-Python: >=3.10,<4.0
Classifier: Development Status :: 4 - Beta
Classifier: Programming Language :: Python :: 3
Classifier: Programming Language :: Python :: 3.10
Classifier: Programming Language :: Python :: 3.11
Classifier: Programming Language :: Python :: 3.12
Classifier: Programming Language :: Python :: 3.13
Classifier: Programming Language :: Python :: 3.14
Requires-Dist: defusedxml (>=0.7.1)
Requires-Dist: gcsfs (>=2025.12.0,<2026.0.0)
Requires-Dist: pandas (>=2.2.0)
Requires-Dist: pandas-stubs (>=2.0.0.230412)
Requires-Dist: types-xmltodict (>=0.13.0.3)
Requires-Dist: xmltodict (>=0.13.0)
Project-URL: Changelog, https://github.com/statisticsnorway/ssb-altinn-python/releases
Project-URL: Documentation, https://statisticsnorway.github.io/ssb-altinn-python
Project-URL: Homepage, https://github.com/statisticsnorway/ssb-altinn-python
Project-URL: Repository, https://github.com/statisticsnorway/ssb-altinn-python
